omnicoreagent/__init__.py
omnicoreagent/core/__init__.py
omnicoreagent/core/constants.py
omnicoreagent/core/context_manager.py
omnicoreagent/core/guardrails.py
omnicoreagent/core/llm.py
omnicoreagent/core/system_prompts.py
omnicoreagent/core/token_usage.py
omnicoreagent/core/tool_response_offloader.py
omnicoreagent/core/types.py
omnicoreagent/core/utils.py
omnicoreagent/core/agents/__init__.py
omnicoreagent/core/agents/base.py
omnicoreagent/core/agents/react_agent.py
omnicoreagent/core/events/__init__.py
omnicoreagent/core/events/base.py
omnicoreagent/core/events/event_router.py
omnicoreagent/core/events/in_memory.py
omnicoreagent/core/events/redis_stream.py
omnicoreagent/core/memory_store/__init__.py
omnicoreagent/core/memory_store/base.py
omnicoreagent/core/memory_store/in_memory.py
omnicoreagent/core/memory_store/memory_router.py
omnicoreagent/core/memory_store/mongodb.py
omnicoreagent/core/memory_store/redis_memory.py
omnicoreagent/core/memory_store/sql_db_memory.py
omnicoreagent/core/skills/__init__.py
omnicoreagent/core/skills/manager.py
omnicoreagent/core/skills/models.py
omnicoreagent/core/skills/tools.py
omnicoreagent/core/summarizer/__init__.py
omnicoreagent/core/summarizer/summarizer_engine.py
omnicoreagent/core/summarizer/summarizer_types.py
omnicoreagent/core/summarizer/tokenizer.py
omnicoreagent/core/tools/__init__.py
omnicoreagent/core/tools/advance_tools_use.py
omnicoreagent/core/tools/artifact_tool.py
omnicoreagent/core/tools/local_tools_registry.py
omnicoreagent/core/tools/tools_handler.py
omnicoreagent/core/tools/advance_tools/__init__.py
omnicoreagent/core/tools/advance_tools/advanced_tools_use.py
omnicoreagent/core/tools/memory_tool/__init__.py
omnicoreagent/core/tools/memory_tool/base.py
omnicoreagent/core/tools/memory_tool/factory.py
omnicoreagent/core/tools/memory_tool/local_storage.py
omnicoreagent/core/tools/memory_tool/memory_tool.py
omnicoreagent/core/tools/memory_tool/r2_storage.py
omnicoreagent/core/tools/memory_tool/s3_storage.py
omnicoreagent-0.3.6.dist-info/METADATA
omnicoreagent-0.3.6.dist-info/WHEEL
omnicoreagent-0.3.6.dist-info/entry_points.txt
omnicoreagent-0.3.6.dist-info/licenses/LICENSE
omnicoreagent-0.3.6.dist-info/RECORD
