Metadata-Version: 2.4
Name: omnicoreagent
Version: 0.3.6
Summary: OmniCoreAgent is a powerful Python AI Agent framework for building autonomous AI agents that think, reason, and execute complex tasks. Production-ready agents that use tools, manage memory, coordinate workflows, and handle real-world business logic.
Project-URL: Repository, https://github.com/omnirexflora-labs/omnicoreagent
Project-URL: Issues, https://github.com/omnirexflora-labs/omnicoreagent/issues
Author-email: Abiola Adeshina <abiolaadedayo1993@gmail.com>
License: MIT
License-File: LICENSE
Keywords: agent,ai,automation,framework,git,llm,mcp
Classifier: Development Status :: 4 - Beta
Classifier: Intended Audience :: Developers
Classifier: License :: OSI Approved :: MIT License
Classifier: Programming Language :: Python :: 3
Classifier: Programming Language :: Python :: 3.10
Classifier: Programming Language :: Python :: 3.11
Classifier: Programming Language :: Python :: 3.12
Classifier: Programming Language :: Python :: 3.13
Requires-Python: >=3.10
Requires-Dist: anyio>=4.2.0
Requires-Dist: apscheduler>=3.11.0
Requires-Dist: boto3>=1.42.37
Requires-Dist: click>=8.1.7
Requires-Dist: colorama>=0.4.6
Requires-Dist: colorlog>=6.9.0
Requires-Dist: cryptography>=45.0.6
Requires-Dist: fastapi-sso>=0.18.0
Requires-Dist: fastapi>=0.115.12
Requires-Dist: httpx-sse>=0.4.0
Requires-Dist: httpx>=0.26.0
Requires-Dist: litellm>=1.75.2
Requires-Dist: mcp[cli]>=1.9.1
Requires-Dist: motor>=3.7.1
Requires-Dist: opik>=1.8.19
Requires-Dist: psutil>=7.0.0
Requires-Dist: psycopg2-binary>=2.9.10
Requires-Dist: pydantic[email]>=2.6.0
Requires-Dist: pymongo>=4.15.1
Requires-Dist: pymupdf>=1.26.3
Requires-Dist: python-decouple>=3.8
Requires-Dist: python-dotenv>=1.0.1
Requires-Dist: python-multipart>=0.0.20
Requires-Dist: redis>=5.2.1
Requires-Dist: rich>=13.9.4
Requires-Dist: sqlalchemy>=2.0.0
Requires-Dist: textual>=7.3.0
Requires-Dist: tiktoken>=0.8.0
Requires-Dist: tzlocal>=5.2
Requires-Dist: uvicorn>=0.34.1
Requires-Dist: websockets>=15.0.1
